alibabacloud_ice20201109/__init__.py
alibabacloud_ice20201109/client.py
alibabacloud_ice20201109/models/__init__.py
alibabacloud_ice20201109/models/_active_ai_rtc_license_request.py
alibabacloud_ice20201109/models/_active_ai_rtc_license_response.py
alibabacloud_ice20201109/models/_active_ai_rtc_license_response_body.py
alibabacloud_ice20201109/models/_add_ad_insertion_request.py
alibabacloud_ice20201109/models/_add_ad_insertion_response.py
alibabacloud_ice20201109/models/_add_ad_insertion_response_body.py
alibabacloud_ice20201109/models/_add_category_request.py
alibabacloud_ice20201109/models/_add_category_response.py
alibabacloud_ice20201109/models/_add_category_response_body.py
alibabacloud_ice20201109/models/_add_editing_project_materials_request.py
alibabacloud_ice20201109/models/_add_editing_project_materials_response.py
alibabacloud_ice20201109/models/_add_editing_project_materials_response_body.py
alibabacloud_ice20201109/models/_add_favorite_public_media_request.py
alibabacloud_ice20201109/models/_add_favorite_public_media_response.py
alibabacloud_ice20201109/models/_add_favorite_public_media_response_body.py
alibabacloud_ice20201109/models/_add_media_connect_flow_input_request.py
alibabacloud_ice20201109/models/_add_media_connect_flow_input_response.py
alibabacloud_ice20201109/models/_add_media_connect_flow_input_response_body.py
alibabacloud_ice20201109/models/_add_media_connect_flow_output_request.py
alibabacloud_ice20201109/models/_add_media_connect_flow_output_response.py
alibabacloud_ice20201109/models/_add_media_connect_flow_output_response_body.py
alibabacloud_ice20201109/models/_add_media_marks_request.py
alibabacloud_ice20201109/models/_add_media_marks_response.py
alibabacloud_ice20201109/models/_add_media_marks_response_body.py
alibabacloud_ice20201109/models/_add_stream_tag_to_search_lib_request.py
alibabacloud_ice20201109/models/_add_stream_tag_to_search_lib_response.py
alibabacloud_ice20201109-6.10.0.dist-info/LICENSE
alibabacloud_ice20201109-6.10.0.dist-info/METADATA
alibabacloud_ice20201109-6.10.0.dist-info/WHEEL
alibabacloud_ice20201109-6.10.0.dist-info/top_level.txt
alibabacloud_ice20201109-6.10.0.dist-info/RECORD
